btrview/__init__.py
btrview/__main__.py
btrview/btrfs.py
btrview/rich_output.py
btrview/subvolume.py
btrview/typed_info.py
btrview/utils.py
btrview/scripts/btrview.py
btrview-0.8.1.dist-info/LICENSE.md
btrview-0.8.1.dist-info/METADATA
btrview-0.8.1.dist-info/WHEEL
btrview-0.8.1.dist-info/entry_points.txt
btrview-0.8.1.dist-info/top_level.txt
btrview-0.8.1.dist-info/RECORD
