Metadata-Version: 2.1
Name: btrview
Version: 0.8.1
Summary: View btrfs snapshot trees
Author: Chris Copley
License: MIT License
Project-URL: Repository, https://github.com/CopOnTheRun/btrview
Project-URL: Issues, https://github.com/CopOnTheRun/btrview/issues
Keywords: btrfs
Classifier: License :: OSI Approved :: MIT License
Classifier: Programming Language :: Python
Classifier: Programming Language :: Python :: 3
Requires-Python: >=3.11
License-File: LICENSE.md
Requires-Dist: treelib
Requires-Dist: rich
Provides-Extra: build
Requires-Dist: build ; extra == 'build'
Requires-Dist: twine ; extra == 'build'
Provides-Extra: dev
Requires-Dist: bumpver ; extra == 'dev'
Requires-Dist: mypy ; extra == 'dev'
Requires-Dist: pip-tools ; extra == 'dev'
